{
    "bookWorld": {
        "åˆ†ç±»": {
            "author": "//dd[@class=\"book_other\"]/span/text()",
            "lastChapterTitle": "(//dd[@class=\"book_other\"])[2]/a/text()",
            "responseFormatType": "html",
            "bookName": "//dd/h3/a/text()",
            "httpHeaders": {
                "referer": "http://www.huanyue1234.com",
                "User-Agent": "Mozilla/5.0 (Windows NT 10.0; Win64; x64) AppleWebKit/537.36 (KHTML, like Gecko) Chrome/100.0.4896.75 Safari/537.36"
            },
            "requestInfo": "@js:\n\nlet url = config.host +\"/book/\"+params.filters.class+\"/\"+params.filters.type+\"-0-\"+params.filters.words+\"-0-0-\"+params.filters.order+\"-\"+params.filters.status+\"-\"+params.pageIndex+\".html\";\n\nreturn {'url':url,'POST':false,'httpHeaders':config.httpHeaders,'cacheTime':3600}",
            "host": "http://www.huanyue1234.com",
            "actionID": "bookWorld",
            "moreKeys": {
                "pageSize": "30",
                "requestFilters": "class\nä¹¦åº“::quanbu\nçŽ„å¹»::xuanhuan\nä»™ä¾ ::xianxia\néƒ½å¸‚::dushi\nå†›å²::lishi\nç½‘æ¸¸::wangyou\nç§‘å¹»::kehuan\nçµå¼‚::lingyi\nè¨€æƒ…::yanqing\nå…¶ä»–::qita\n\ntype\nå…¨éƒ¨::default\næ€»ç‚¹å‡»::allvisit\næœˆç‚¹å‡»::monthvisit\nå‘¨ç‚¹å‡»::weekvisit\næ—¥ç‚¹å‡»::dayvisit\næ€»æŽ¨è::allvote\næ€»æ”¶è—::goodnum\nå­—æ•°::size\nå…¥ç«™æ—¶é—´::postdate\næ›´æ–°æ—¶é—´::lastupdate\n\nwords\nå…¨éƒ¨::0\n30ä¸‡ä»¥ä¸‹::1\n30ä¸‡-50ä¸‡::2\n50ä¸‡-100ä¸‡::3\n100ä¸‡-200ä¸‡::4\n200ä¸‡ä»¥ä¸Š::5\n\norder\nå…¨éƒ¨::0\nè¿žè½½::1\nå®Œæœ¬::2\n\nstatus\nå€’åº::0\næ­£åº::1\n"
            },
            "cover": "//dt//img/@src",
            "desc": "//dd[@class=\"book_des\"]/text()",
            "list": "//div[@class=\"sitebox\"]/dl",
            "parserID": "DOM",
            "detailUrl": "//dt/a/@href",
            "validConfig": ""
        }
    },
    "weight": "4444",
    "miniAppVersion": "2.53.2",
    "chapterList": {
        "actionID": "chapterList",
        "validConfig": "",
        "requestInfo": "@js:\n\nif(result.indexOf(\"_\")!=-1){\n\nlet res = result.split(\"_\")\nlet url = config.host+\"/book\"+res[0]+'/'+res[1]\n\nreturn {'url':url,'POST':false,'httpHeaders':config.httpHeaders,'cacheTime':3600};\n}else{\n\nreturn {'url':result,'POST':false,'httpHeaders':config.httpHeaders,'cacheTime':3600};\n\n}",
        "title": "//a/text()",
        "host": "http://www.huanyue1234.com",
        "httpHeaders": {
            "referer": "http://www.huanyue1234.com",
            "User-Agent": "Mozilla/5.0 (Windows NT 10.0; Win64; x64) AppleWebKit/537.36 (KHTML, like Gecko) Chrome/100.0.4896.75 Safari/537.36"
        },
        "list": "//div[@class=\"book_list\"]/ul/li",
        "responseFormatType": "html",
        "parserID": "DOM",
        "url": "//a/@href"
    },
    "searchShudan": {
        "actionID": "searchShudan",
        "parserID": "DOM"
    },
    "relatedWord": {
        "actionID": "relatedWord",
        "parserID": "DOM"
    },
    "enable": 0,
    "sourceName": "ðŸ‘¾å¹»æœˆä¹¦å±‹",
    "sourceType": "text",
    "sourceUrl": "http://www.huanyue1234.com",
    "httpHeaders": {
        "referer": "http://www.huanyue1234.com",
        "User-Agent": "Mozilla/5.0 (Windows NT 10.0; Win64; x64) AppleWebKit/537.36 (KHTML, like Gecko) Chrome/100.0.4896.75 Safari/537.36"
    },
    "shudanDetail": {
        "actionID": "shudanDetail",
        "parserID": "DOM"
    },
    "lastModifyTime": "1650355551.039780",
    "searchBook": {
        "author": "(//p[@class=\"author\"])[1]/text() ||@js:\n\nlet name = result.match(/ä½œè€…ï¼š(.*)/)[1]\nreturn name",
        "responseFormatType": "html",
        "bookName": "//p[@class=\"title\"]/text()",
        "httpHeaders": {
            "referer": "http://www.huanyue1234.com",
            "User-Agent": "Mozilla/5.0 (Windows NT 10.0; Win64; x64) AppleWebKit/537.36 (KHTML, like Gecko) Chrome/100.0.4896.75 Safari/537.36"
        },
        "requestInfo": "@js:\n\nlet url  = config.host.replace(\"www\",\"m\") +\"/s.php\";\nlet hp = {\n    \"keyword\":params.keyWord,\n    \"t\":\"1\"\n}\n\nlet hh = {\n    \"User-Agent\": \" Mozilla/5.0 (iPhone; CPU iPhone OS 13_2_3 like Mac OS X) AppleWebKit/605.1.15 (KHTML, like Gecko) Version/13.0.3 Mobile/15E148 Safari/604.1\",\n    \"referer\": \" http://m.huanyue1234.com/\"\n}\n\nreturn {'url':url,'POST':true,'httpHeaders':hh,'httpParams':hp,'cacheTime':3600}",
        "host": "http://www.huanyue1234.com",
        "actionID": "searchBook",
        "moreKeys": {
            "maxPage": 1
        },
        "detailUrl": "//a/@href",
        "validConfig": "",
        "list": "//div[@class=\"recommend mybook\"]/div[position()>1]",
        "parserID": "DOM",
        "cover": "//a/@href ||@js:\n\nlet res = result.split(\"_\")\nlet url = \"http://www.huanyue1234.com/files/article/image/\"+res[0]+\"/\"+res[1]+\"/\"+res[1]+\"s.jpg\"\nreturn url",
        "status": "(//p[@class=\"author\"])[2]/text() ||@js:\n\nlet name = result.match(/(.*?)\\s+| æ›´æ–°/)[1]\nreturn name"
    },
    "chapterContent": {
        "actionID": "chapterContent",
        "content": "//div[@id=\"htmlContent\"]//text() ||@js: return result.replace(/ç« èŠ‚é”™è¯¯.*/,\"\")",
        "validConfig": "",
        "requestInfo": "@js:\n\nreturn {'url':result,'POST':false,'httpHeaders':config.httpHeaders,'cacheTime':3600};",
        "host": "http://www.huanyue1234.com",
        "httpHeaders": {
            "referer": "http://www.huanyue1234.com",
            "User-Agent": "Mozilla/5.0 (Windows NT 10.0; Win64; x64) AppleWebKit/537.36 (KHTML, like Gecko) Chrome/100.0.4896.75 Safari/537.36"
        },
        "responseFormatType": "html",
        "parserID": "DOM"
    },
    "shupingList": {
        "actionID": "shupingList",
        "parserID": "DOM"
    },
    "shudanList": {},
    "authorId": "",
    "shupingHome": {
        "actionID": "shupingHome",
        "parserID": "DOM"
    },
    "bookDetail": {
        "validConfig": "",
        "actionID": "bookDetail",
        "requestInfo": "@js:\n\nif(result.indexOf(\"_\")!=-1){\n\nlet res = result.split(\"_\")\nlet url = config.host+\"/book\"+res[0]+'/'+res[1]\n\nreturn {'url':url,'POST':false,'httpHeaders':config.httpHeaders,'cacheTime':3600};\n}else{\n\nreturn {'url':result,'POST':false,'httpHeaders':config.httpHeaders,'cacheTime':3600};\n\n}",
        "host": "http://www.huanyue1234.com",
        "httpHeaders": {
            "referer": "http://www.huanyue1234.com",
            "User-Agent": "Mozilla/5.0 (Windows NT 10.0; Win64; x64) AppleWebKit/537.36 (KHTML, like Gecko) Chrome/100.0.4896.75 Safari/537.36"
        },
        "responseFormatType": "html",
        "parserID": "DOM",
        "desc": "//h3[@class=\"bookinfo_intro\"]/div/following-sibling::text()"
    }
}